mcp_http_to_stdio/__init__.py
mcp_http_to_stdio/__main__.py
mcp_http_to_stdio/bridge.py
mcp_http_to_stdio-0.1.1.dist-info/licenses/LICENSE
mcp_http_to_stdio-0.1.1.dist-info/METADATA
mcp_http_to_stdio-0.1.1.dist-info/WHEEL
mcp_http_to_stdio-0.1.1.dist-info/entry_points.txt
mcp_http_to_stdio-0.1.1.dist-info/top_level.txt
mcp_http_to_stdio-0.1.1.dist-info/RECORD
