Metadata-Version: 2.4
Name: mcp-http-to-stdio
Version: 0.1.1
Summary: Bridge utility enabling Claude Desktop to connect to HTTP-based MCP servers via stdio transport
Author: Agentic Enterprise
Maintainer: Agentic Enterprise
License: MIT
Project-URL: Homepage, https://github.com/agentic-enterprise/mcp-http-to-stdio
Project-URL: Repository, https://github.com/agentic-enterprise/mcp-http-to-stdio
Project-URL: Bug Tracker, https://github.com/agentic-enterprise/mcp-http-to-stdio/issues
Project-URL: Documentation, https://github.com/agentic-enterprise/mcp-http-to-stdio#readme
Keywords: mcp,model-context-protocol,claude,claude-desktop,anthropic,http,stdio,bridge,proxy,json-rpc,protocol-bridge
Classifier: Development Status :: 4 - Beta
Classifier: Intended Audience :: Developers
Classifier: License :: OSI Approved :: MIT License
Classifier: Programming Language :: Python :: 3
Classifier: Programming Language :: Python :: 3.8
Classifier: Programming Language :: Python :: 3.9
Classifier: Programming Language :: Python :: 3.10
Classifier: Programming Language :: Python :: 3.11
Classifier: Programming Language :: Python :: 3.12
Classifier: Programming Language :: Python :: 3.13
Classifier: Topic :: Software Development :: Libraries :: Python Modules
Classifier: Topic :: System :: Networking
Classifier: Topic :: Communications
Classifier: Topic :: Internet :: Proxy Servers
Requires-Python: >=3.8
License-File: LICENSE
Requires-Dist: requests>=2.32.0
Dynamic: license-file
